calspec_data/calspec.csv
calspec_data/history.csv
getCalspec/__init__.py
getCalspec/_version.py
getCalspec/getCalspec.py
getCalspec/rebuild.py
getcalspec-2.3.4.dist-info/licenses/LICENSE
getcalspec-2.3.4.dist-info/METADATA
getcalspec-2.3.4.dist-info/WHEEL
getcalspec-2.3.4.dist-info/top_level.txt
getcalspec-2.3.4.dist-info/RECORD
