Metadata-Version: 2.4
Name: getCalspec
Version: 2.3.4
Summary: Python package to download Calspec spectra
Author-email: "J. Neveu" <jeremy.neveu@universite-paris-saclay.fr>
License: BSD-3-Clause
Project-URL: Homepage, https://github.com/LSSTDESC/getCalspec
Project-URL: Documentation, https://getcalspec.readthedocs.io
Project-URL: Repository, https://github.com/LSSTDESC/getCalspec
Classifier: Development Status :: 4 - Beta
Classifier: Intended Audience :: Science/Research
Classifier: License :: OSI Approved :: BSD License
Classifier: Programming Language :: Python :: 3
Classifier: Programming Language :: Python :: 3.7
Classifier: Programming Language :: Python :: 3.8
Classifier: Programming Language :: Python :: 3.9
Classifier: Programming Language :: Python :: 3.10
Classifier: Programming Language :: Python :: 3.11
Classifier: Topic :: Scientific/Engineering :: Astronomy
Requires-Python: >=3.7
License-File: LICENSE
Requires-Dist: numpy>1.15
Requires-Dist: matplotlib>3.1
Requires-Dist: pandas
Requires-Dist: astropy
Requires-Dist: astroquery
Requires-Dist: lxml
Requires-Dist: beautifulsoup4
Provides-Extra: test
Requires-Dist: pytest; extra == "test"
Requires-Dist: pytest-flake8; extra == "test"
Provides-Extra: docs
Requires-Dist: sphinx; extra == "docs"
Requires-Dist: sphinx-rtd-theme; extra == "docs"
Dynamic: license-file
